MANIFEST.in
README.rst
requirements-test.txt
requirements.txt
setup.py
jasco_parser/__init__.py
jasco_parser.egg-info/PKG-INFO
jasco_parser.egg-info/SOURCES.txt
jasco_parser.egg-info/dependency_links.txt
jasco_parser.egg-info/requires.txt
jasco_parser.egg-info/top_level.txt
jasco_parser.egg-info/zip-safe
tests/__init__.py
tests/test_parser.py